MANIFEST.in
README.rst
requirements.txt
setup.py
bolt/__init__.py
bolt/base.py
bolt/construct.py
bolt/factory.py
bolt/utils.py
bolt/local/__init__.py
bolt/local/array.py
bolt/local/construct.py
bolt/spark/__init__.py
bolt/spark/array.py
bolt/spark/chunk.py
bolt/spark/construct.py
bolt/spark/shapes.py
bolt/spark/stack.py
bolt/spark/statcounter.py
bolt/spark/utils.py
bolt_python.egg-info/PKG-INFO
bolt_python.egg-info/SOURCES.txt
bolt_python.egg-info/dependency_links.txt
bolt_python.egg-info/requires.txt
bolt_python.egg-info/top_level.txt
test/test_utils.py