Metadata-Version: 1.0
Name: bolt-python
Version: 0.3.2
Summary: Unified and scalable interface for multidimensional arrays
Home-page: https://github.com/bolt-project/bolt
Author: The Freeman Lab
Author-email: the.freeman.lab@gmail.com
License: UNKNOWN
Platform: UNKNOWN
